groupdocs/comparison/py.typed
aspose/pycore/py.typed
aspose/pycore/__init__.pyi
aspose/pyreflection/py.typed
aspose/pyreflection/__init__.pyi
aspose/pydrawing/py.typed
aspose/pydrawing/__init__.pyi
aspose/pydrawing/design.pyi
aspose/pydrawing/drawing2d.pyi
aspose/pydrawing/imaging.pyi
aspose/pydrawing/printing.pyi
aspose/pydrawing/text.pyi
groupdocs/comparison/__init__.pyi
groupdocs/comparison/cells/__init__.pyi
groupdocs/comparison/cells/style/__init__.pyi
groupdocs/comparison/common/__init__.pyi
groupdocs/comparison/common/exceptions/__init__.pyi
groupdocs/comparison/interfaces/__init__.pyi
groupdocs/comparison/localization/__init__.pyi
groupdocs/comparison/logging/__init__.pyi
groupdocs/comparison/options/__init__.pyi
groupdocs/comparison/result/__init__.pyi
groupdocs/comparison/words/__init__.pyi
groupdocs/comparison/words/revision/__init__.pyi
groupdocs/__init__.py
groupdocs/comparison.cp310-win_amd64.pyd
groupdocs/comparison.cp311-win_amd64.pyd
groupdocs/comparison.cp312-win_amd64.pyd
groupdocs/comparison.cp313-win_amd64.pyd
groupdocs/comparison.cp35-win_amd64.pyd
groupdocs/comparison.cp36-win_amd64.pyd
groupdocs/comparison.cp37-win_amd64.pyd
groupdocs/comparison.cp38-win_amd64.pyd
groupdocs/comparison.cp39-win_amd64.pyd
groupdocs/pycore.cp310-win_amd64.pyd
groupdocs/pycore.cp311-win_amd64.pyd
groupdocs/pycore.cp312-win_amd64.pyd
groupdocs/pycore.cp313-win_amd64.pyd
groupdocs/pycore.cp35-win_amd64.pyd
groupdocs/pycore.cp36-win_amd64.pyd
groupdocs/pycore.cp37-win_amd64.pyd
groupdocs/pycore.cp38-win_amd64.pyd
groupdocs/pycore.cp39-win_amd64.pyd
groupdocs/pydrawing.cp310-win_amd64.pyd
groupdocs/pydrawing.cp311-win_amd64.pyd
groupdocs/pydrawing.cp312-win_amd64.pyd
groupdocs/pydrawing.cp313-win_amd64.pyd
groupdocs/pydrawing.cp35-win_amd64.pyd
groupdocs/pydrawing.cp36-win_amd64.pyd
groupdocs/pydrawing.cp37-win_amd64.pyd
groupdocs/pydrawing.cp38-win_amd64.pyd
groupdocs/pydrawing.cp39-win_amd64.pyd
groupdocs/pygc.cp310-win_amd64.pyd
groupdocs/pygc.cp311-win_amd64.pyd
groupdocs_comparison_net-25.12.dist-info/METADATA
groupdocs_comparison_net-25.12.dist-info/WHEEL
groupdocs_comparison_net-25.12.dist-info/entry_points.txt
groupdocs_comparison_net-25.12.dist-info/top_level.txt
groupdocs_comparison_net-25.12.dist-info/RECORD
